mobile_recorder-0.1.0.dist-info/licenses/LICENSE
src/__init__.py
src/recorder.py
mobile_recorder-0.1.0.dist-info/METADATA
mobile_recorder-0.1.0.dist-info/WHEEL
mobile_recorder-0.1.0.dist-info/top_level.txt
mobile_recorder-0.1.0.dist-info/RECORD
