Metadata-Version: 2.4
Name: mobile_recorder
Version: 0.1.0
Summary: Record Android device screens and run operations using uiautomator2
Home-page: https://github.com/raisfeld-ori/mobile_recorder
Author: Ori Raisfeld
Author-email: Ori Raisfeld <raisfeldori@gmail.com>
License: MIT
Requires-Python: >=3.7
License-File: LICENSE
Requires-Dist: uiautomator2>=3.3.3
Dynamic: author
Dynamic: home-page
Dynamic: license-file
Dynamic: requires-python
